psychopy_legacy/__init__.py
psychopy_legacy/components/__init__.py
psychopy_legacy/components/patch/__init__.py
psychopy_legacy/components/patch/classic/patch.png
psychopy_legacy/components/patch/dark/patch.png
psychopy_legacy/components/patch/dark/patch@2x.png
psychopy_legacy/components/patch/light/patch.png
psychopy_legacy/components/patch/light/patch@2x.png
psychopy_legacy/components/ratingScale/__init__.py
psychopy_legacy/components/ratingScale/classic/ratingscale.png
psychopy_legacy/components/ratingScale/classic/ratingscale@2x.png
psychopy_legacy/components/ratingScale/dark/ratingScale@2x.png
psychopy_legacy/components/ratingScale/dark/ratingscale.png
psychopy_legacy/components/ratingScale/light/ratingScale@2x.png
psychopy_legacy/components/ratingScale/light/ratingscale.png
psychopy_legacy/visual/__init__.py
psychopy_legacy/visual/movie2.py
psychopy_legacy/visual/movie3.py
psychopy_legacy/visual/patch.py
psychopy_legacy/visual/ratingscale.py
psychopy_legacy/voicekey/__init__.py
psychopy_legacy/voicekey/demo_vks.py
psychopy_legacy/voicekey/labjack_vks.py
psychopy_legacy/voicekey/parallel_vks.py
psychopy_legacy/voicekey/signal.py
psychopy_legacy/voicekey/vk_tools.py
psychopy_legacy-1.1.1.dist-info/METADATA
psychopy_legacy-1.1.1.dist-info/WHEEL
psychopy_legacy-1.1.1.dist-info/entry_points.txt
psychopy_legacy-1.1.1.dist-info/top_level.txt
psychopy_legacy-1.1.1.dist-info/RECORD
